[
    {
        "key": "datr",
        "value": "-5VYZpcdRXLqdd1arWQRnduC",
        "domain": "facebook.com",
        "path": "/",
        "hostOnly": false,
        "creation": "2024-06-02T07:35:56.822Z",
        "lastAccessed": "2024-06-02T07:35:56.822Z"
    },
    {
        "key": "sb",
        "value": "-5VYZjFLRXbJeX96wVCZBypb",
        "domain": "facebook.com",
        "path": "/",
        "hostOnly": false,
        "creation": "2024-06-02T07:35:56.822Z",
        "lastAccessed": "2024-06-02T07:35:56.822Z"
    },
    {
        "key": "ps_n",
        "value": "1",
        "domain": "facebook.com",
        "path": "/",
        "hostOnly": false,
        "creation": "2024-06-02T07:35:56.822Z",
        "lastAccessed": "2024-06-02T07:35:56.822Z"
    },
    {
        "key": "ps_l",
        "value": "1",
        "domain": "facebook.com",
        "path": "/",
        "hostOnly": false,
        "creation": "2024-06-02T07:35:56.822Z",
        "lastAccessed": "2024-06-02T07:35:56.822Z"
    },
    {
        "key": "fr",
        "value": "0g1qEULLjfdAsDlek.AWUFXEJ0cWk33ODsDdvopoRkzk4.BmWJX7..AAA.0.0.BmXBpb.AWX36r-pZic",
        "domain": "facebook.com",
        "path": "/",
        "hostOnly": false,
        "creation": "2024-06-02T07:35:56.822Z",
        "lastAccessed": "2024-06-02T07:35:56.822Z"
    },
    {
        "key": "c_user",
        "value": "61559106792475",
        "domain": "facebook.com",
        "path": "/",
        "hostOnly": false,
        "creation": "2024-06-02T07:35:56.822Z",
        "lastAccessed": "2024-06-02T07:35:56.822Z"
    },
    {
        "key": "xs",
        "value": "13%3AX7MhbxRat0mWJw%3A2%3A1717312092%3A-1%3A15903",
        "domain": "facebook.com",
        "path": "/",
        "hostOnly": false,
        "creation": "2024-06-02T07:35:56.822Z",
        "lastAccessed": "2024-06-02T07:35:56.822Z"
    },
    {
        "key": "m_page_voice",
        "value": "61559106792475",
        "domain": "facebook.com",
        "path": "/",
        "hostOnly": false,
        "creation": "2024-06-02T07:35:56.822Z",
        "lastAccessed": "2024-06-02T07:35:56.822Z"
    },
    {
        "key": "wd",
        "value": "360x560",
        "domain": "facebook.com",
        "path": "/",
        "hostOnly": false,
        "creation": "2024-06-02T07:35:56.822Z",
        "lastAccessed": "2024-06-02T07:35:56.822Z"
    },
    {
        "key": "locale",
        "value": "en_GB",
        "domain": "facebook.com",
        "path": "/",
        "hostOnly": false,
        "creation": "2024-06-02T07:35:56.822Z",
        "lastAccessed": "2024-06-02T07:35:56.822Z"
    },
    {
        "key": "vpd",
        "value": "v1%3B560x360x2",
        "domain": "facebook.com",
        "path": "/",
        "hostOnly": false,
        "creation": "2024-06-02T07:35:56.822Z",
        "lastAccessed": "2024-06-02T07:35:56.823Z"
    },
    {
        "key": "fbl_st",
        "value": "101530326%3BT%3A28621895",
        "domain": "facebook.com",
        "path": "/",
        "hostOnly": false,
        "creation": "2024-06-02T07:35:56.823Z",
        "lastAccessed": "2024-06-02T07:35:56.823Z"
    },
    {
        "key": "wl_cbv",
        "value": "v2%3Bclient_version%3A2518%3Btimestamp%3A1717313715",
        "domain": "facebook.com",
        "path": "/",
        "hostOnly": false,
        "creation": "2024-06-02T07:35:56.823Z",
        "lastAccessed": "2024-06-02T07:35:56.823Z"
    }
] 
